[
	{
		"lastName" : "Chtira ",
		"firstName" : "Mehdi",
		"campus" : "Paris",
		"promo" : "2018" 
	},

	{
		"lastName" : "Langevin ",
		"firstName" : "Pierre",
		"campus" : "Toulouse",
		"promo" : "2018" 
	},

	{
		"lastName" : "Benamou",
		"firstName" : "Serge",
		"campus" : "Toulouse",
		"promo" : "2016" 
	},

	{
		"lastName" : "Bui",
		"firstName" : "Alexandra",
		"campus" : "Paris",
		"promo" : "2016" 
	},

	{
		"lastName" : "Latorre",
		"firstName" : "Yvan",
		"campus" : "Paris",
		"promo" : "2018" 
	},

	{
		"lastName" : "Berguer",
		"firstName" : "Sabrina",
		"campus" : "Paris",
		"promo" : "2018" 
	},
	
	{
		"lastName" : "Chtira ",
		"firstName" : "Mehdi",
		"campus" : "Paris",
		"promo" : "2017" 
	},

	{
		"lastName" : "Langevin ",
		"firstName" : "Pierre",
		"campus" : "Toulouse",
		"promo" : "2018" 
	},

	{
		"lastName" : "Benamou",
		"firstName" : "Serge",
		"campus" : "Paris",
		"promo" : "2018" 
	},

	{
		"lastName" : "Bui",
		"firstName" : "Alexandra",
		"campus" : "Paris",
		"promo" : "2018" 
	},

	{
		"lastName" : "BlaBlatorre",
		"firstName" : "Yvan",
		"campus" : "Paris",
		"promo" : "2018" 
	},

	{
		"lastName" : "Berguer",
		"firstName" : "Sabrina",
		"campus" : "Paris",
		"promo" : "2016" 
	},

	{
		"lastName" : "Chtira ",
		"firstName" : "Mehdi",
		"campus" : "La Loupe",
		"promo" : "2018" 
	},

	{
		"lastName" : "Langevin ",
		"firstName" : "Pierre",
		"campus" : "Paris",
		"promo" : "2018" 
	},

	{
		"lastName" : "Benamou",
		"firstName" : "Serge",
		"campus" : "Paris",
		"promo" : "2018" 
	},

	{
		"lastName" : "Bui",
		"firstName" : "Alexandra",
		"campus" : "Paris",
		"promo" : "2018" 
	},

	{
		"lastName" : "Latorre",
		"firstName" : "Yvan",
		"campus" : "Paris",
		"promo" : "2018" 
	},

	{
		"lastName" : "Berguer",
		"firstName" : "Sabrina",
		"campus" : "Paris",
		"promo" : "2018" 
	},
	
	{
		"lastName" : " Chtira ",
		"firstName" : "Mehdi",
		"campus" : "Paris",
		"promo" : "2018" 
	},

	{
		"lastName" : "Langevin ",
		"firstName" : "Pierre",
		"campus" : "Paris",
		"promo" : "2018" 
	},

	{
		"lastName" : "Benamou",
		"firstName" : "Serge",
		"campus" : "Paris",
		"promo" : "2018" 
	},

	{
		"lastName" : "Bui",
		"firstName" : "Alexandra",
		"campus" : "Paris",
		"promo" : "2018" 
	},

	{
		"lastName" : "Latorre",
		"firstName" : "Yvan",
		"campus" : "Paris",
		"promo" : "2018" 
	},

	{
		"lastName" : "Berguer",
		"firstName" : "Sabrina",
		"campus" : "Paris",
		"promo" : "2018" 
	},
]
